pe/__init__.py
pe/_autoignore.py
pe/_constants.py
pe/_cy_machine.c
pe/_cy_machine.cp310-win_amd64.pyd
pe/_cy_machine.pyi
pe/_cy_machine.pyx
pe/_debug.py
pe/_definition.py
pe/_disarm.py
pe/_errors.py
pe/_escape.py
pe/_functions.py
pe/_grammar.py
pe/_match.py
pe/_meta.py
pe/_misc.py
pe/_optimize.py
pe/_parse.py
pe/_parser.py
pe/_py_machine.py
pe/_types.py
pe/actions.py
pe/machine.py
pe/operators.py
pe/packrat.py
pe/patterns.py
pe-0.6.0.dist-info/licenses/LICENSE
pe-0.6.0.dist-info/METADATA
pe-0.6.0.dist-info/WHEEL
pe-0.6.0.dist-info/top_level.txt
pe-0.6.0.dist-info/RECORD
