Metadata-Version: 2.4
Name: pe
Version: 0.6.0
Summary: Library for Parsing Expression Grammars (PEG)
Author-email: Michael Wayne Goodman <goodman.m.w@gmail.com>
License: MIT License
Project-URL: Homepage, https://github.com/goodmami/pe
Project-URL: Documentation, https://github.com/goodmami/pe/blob/main/docs/README.md
Project-URL: Changelog, https://github.com/goodmami/pe/blob/main/CHANGELOG.md
Keywords: peg,parsing,text
Classifier: Development Status :: 4 - Beta
Classifier: Environment :: Console
Classifier: Intended Audience :: Developers
Classifier: License :: OSI Approved :: MIT License
Classifier: Programming Language :: Cython
Classifier: Programming Language :: Python
Classifier: Programming Language :: Python :: 3
Classifier: Programming Language :: Python :: 3.9
Classifier: Programming Language :: Python :: 3.10
Classifier: Programming Language :: Python :: 3.11
Classifier: Programming Language :: Python :: 3.12
Classifier: Programming Language :: Python :: 3.13
Classifier: Topic :: Software Development :: Libraries :: Python Modules
Classifier: Topic :: Text Processing
Classifier: Topic :: Utilities
Requires-Python: >=3.9
License-File: LICENSE
Provides-Extra: dev
Requires-Dist: pytest; extra == "dev"
Requires-Dist: ruff; extra == "dev"
Requires-Dist: mypy; extra == "dev"
Dynamic: license-file
